pgalchemy/__init__.py
pgalchemy/alembic/__init__.py
pgalchemy/alembic/column_privilege.py
pgalchemy/alembic/comparator.py
pgalchemy/alembic/operations/__init__.py
pgalchemy/alembic/operations/cls.py
pgalchemy/alembic/operations/rls.py
pgalchemy/cls.py
pgalchemy/domains.py
pgalchemy/expressions.py
pgalchemy/functions.py
pgalchemy/policy.py
pgalchemy/rls.py
pgalchemy/types.py
pgalchemy/views.py
pgalchemy-0.1.6.dist-info/LICENSE
pgalchemy-0.1.6.dist-info/METADATA
pgalchemy-0.1.6.dist-info/WHEEL
pgalchemy-0.1.6.dist-info/RECORD
