Metadata-Version: 2.3
Name: pgalchemy
Version: 0.1.6
Summary: 
Author: Matthew Beatty
Author-email: beattyml1@gmail.com
Requires-Python: >=3.11,<4.0
Classifier: Programming Language :: Python :: 3
Classifier: Programming Language :: Python :: 3.11
Classifier: Programming Language :: Python :: 3.12
Classifier: Programming Language :: Python :: 3.13
Requires-Dist: alembic (>=1.13.2,<2.0.0)
Requires-Dist: alembic-utils (>=0.8.4,<0.9.0)
Requires-Dist: sqlalchemy (>=2.0.32,<3.0.0)
